clustr/Building.py
clustr/DebugDevice.py
clustr/Generate.py
clustr/S_Clustr_Client.py
clustr/S_Clustr_Server.py
clustr/Server.conf
clustr/Testpc.py
clustr/Version.conf
clustr/__init__.py
clustr/blacklist.conf
clustr/game.py
clustr/scc.py
clustr/scctest.py
clustr/clustr_lib/__init__.py
clustr/clustr_lib/aes.py
clustr/pack/DingTalkPush.py
clustr/pack/S_Clustr_AES.py
clustr/pack/__init__.py
S_Clustr_DSL-1.3.7.dist-info/LICENSE
S_Clustr_DSL-1.3.7.dist-info/METADATA
S_Clustr_DSL-1.3.7.dist-info/WHEEL
S_Clustr_DSL-1.3.7.dist-info/entry_points.txt
S_Clustr_DSL-1.3.7.dist-info/top_level.txt
S_Clustr_DSL-1.3.7.dist-info/RECORD
