Metadata-Version: 2.1
Name: S-Clustr-DSL
Version: 1.3.7
Summary: A simple DSL for S-Clustr
Author: Maptnh@S-H4CK13
Classifier: Development Status :: 3 - Alpha
Classifier: Intended Audience :: Developers
Classifier: License :: OSI Approved :: MIT License
Classifier: Programming Language :: Python :: 3
Classifier: Programming Language :: Python :: 3.7
Classifier: Programming Language :: Python :: 3.8
Classifier: Programming Language :: Python :: 3.9
Classifier: Programming Language :: Python :: 3.10
Classifier: Programming Language :: Python :: 3.11
Classifier: Programming Language :: Python :: 3.12
Requires-Python: >=3.7
License-File: LICENSE
Requires-Dist: certifi ==2023.7.22
Requires-Dist: charset-normalizer ==3.3.0
Requires-Dist: colorama ==0.4.6
Requires-Dist: idna ==3.4
Requires-Dist: loguru ==0.7.2
Requires-Dist: pycryptodome ==3.19.0
Requires-Dist: requests ==2.31.0
Requires-Dist: urllib3 ==2.0.6
Requires-Dist: win32-setctime ==1.1.0
Requires-Dist: PyQt5 ==5.15.9
